langchain_compass/__init__.py
langchain_compass/model_generator.py
langchain_compass/openapi_tool_maker.py
langchain_compass/openapi_tool_maker2.notpy
langchain_compass/params_converter.py
langchain_compass/py.typed
langchain_compass/toolkits.py
langchain_compass-0.4.1.dist-info/LICENSE
langchain_compass-0.4.1.dist-info/METADATA
langchain_compass-0.4.1.dist-info/WHEEL
langchain_compass-0.4.1.dist-info/RECORD
